[
    {
        "company_name": "Minitab",
        "location": "München - DE",
        "description": "Seit über 50 Jahren hilft Minitab Unternehmen und Institutionen, Trends zu erkennen, Probleme zu lösen und wertvolle Erkenntnisse aus Daten zu gewinnen. ...",
        "stand": "Halle 15, Stand H53",
        "product_link": "/aussteller/minitab/N1549225",
        "search_snippet_type": "Aussteller 2025"
    },
    {
        "company_name": "Projektron",
        "location": "Berlin - DE",
        "description": "Die Projektron GmbH entwickelt und vertreibt seit 2001 mit derzeit mehr als 100 Mitarbeitern die webbasierte Projektmanagement-Software Projektron BCS. ...",
        "stand": "Halle 15, Stand B18",
        "product_link": "/aussteller/projektron/N1507677",
        "search_snippet_type": "Aussteller 2025"
    },
    {
        "company_name": "SABO Mobile IT",
        "location": "Bühl - DE",
        "description": "SABO Mobile IT ist ein kompetenter und erfahrener Auftragsentwickler von kundenspezifischen Innovationen zur Digitalisierung der Produktion und Industrie ...",
        "stand": "Halle 9, Stand F18/8",
        "product_link": "/aussteller/sabo-mobile-it/N1574727",
        "search_snippet_type": "Aussteller 2025"
    },
    {
        "company_name": "Schneider Electric",
        "location": "Rueil Malmaison - FR",
        "description": "Fachleute aus der Industrie treffen bei unseren Innovation Talks, Smart Factory Experiences, Guided Tours auf unsere Experten für Industrieautomatisierung: ...",
        "stand": "Freigelände, In der 3. Allee, zwischen der Ostwand Halle 11 und dem\nKonrad-Zuse-Par, Stand V125",
        "product_link": "/aussteller/schneider-electric/N1544704",
        "search_snippet_type": "Aussteller 2025"
    },
    {
        "company_name": "ServiceNow",
        "location": "München - DE",
        "description": "Besuchen Sie uns auf der diesjährigen Hannover Messe, wo wir gemeinsam die digitale Fabrik der Zukunft gestalten. ServiceNow unterstützt Hersteller ...",
        "stand": "Halle 15, Stand D72",
        "product_link": "/aussteller/servicenow/N1433719",
        "search_snippet_type": "Aussteller 2025"
    },
    {
        "company_name": "Shanghai Xuyu Information",
        "location": "Shanghai - CN",
        "description": "Xuyu Information Technology wurde 2004 gegründet und ist heute ein führender Anbieter integrierter IoT-Lösungen in China. Sein grundlegendes Ziel ist es, ...",
        "stand": "Halle 15, Stand A02",
        "product_link": "/aussteller/shanghai-xuyu-information/N1573209",
        "search_snippet_type": "Aussteller 2025"
    },
    {
        "company_name": "STIFT",
        "location": "Erfurt - DE",
        "description": "Die Stiftung für Technologie, Innovation und Forschung Thüringen (STIFT) fördert seit ihrer Gründung 1993 selbstlos Wissenschaft, Forschung, Technologie ...",
        "stand": "Halle 2, Stand D28",
        "product_link": "/aussteller/stift/N1439994",
        "search_snippet_type": "Aussteller 2025"
    },
    {
        "company_name": "TeamViewer Germany",
        "location": "Göppingen - DE",
        "description": "Über TeamViewer\n\nAls globales Technologieunternehmen und mit dem Angebot einer führenden Konnektivitätsplattform ermöglicht es TeamViewer, aus der Ferne ...",
        "stand": "Halle 14, Stand H70",
        "product_link": "/aussteller/teamviewer-germany/N1546981",
        "search_snippet_type": "Aussteller 2025"
    },
    {
        "company_name": "TechnoGIS",
        "location": "Sleman - ID",
        "description": "Techno GIS Indonesia ist ein Geospatial-Unternehmen, das bahnbrechende Innovationen in der Produktentwicklung in verschiedenen Vermessungsbereichen ...",
        "stand": "Halle 2, Stand D36/6",
        "product_link": "/aussteller/technogis/N1549090",
        "search_snippet_type": "Aussteller 2025"
    },
    {
        "company_name": "ZVEI e. V.",
        "location": "Frankfurt - DE",
        "description": "ZVEI: Der Verband der Elektro- und Digitalindustrie\n\nDer ZVEI vertritt die gemeinsamen Interessen der Elektro- und Digitalindustrie und der zugehörigen ...",
        "stand": "Halle 11, Stand B54",
        "product_link": "/aussteller/zvei-e-v-/N1540027",
        "search_snippet_type": "Aussteller 2025"
    },
    {
        "company_name": "Rootstock Software",
        "location": "San Ramon, CA 94583 - USA",
        "description": "... Rootstock Software develops and implements cloud Enterprise Resource Planning (ERP) software that helps companies ...",
        "stand": "Halle 15, Stand B04",
        "product_link": "/aussteller/rootstock-software/N1574319",
        "search_snippet_type": "Aussteller 2025"
    },
    {
        "company_name": "Bundesamt für Sicherheit BSI",
        "location": "Bonn - DE",
        "description": "Das Bundesamt für Sicherheit in der Informationstechnik (BSI) wurde am 01.01.1991 gegründet und gehört zum Geschäftsbereich des Bundesministeriums des ...",
        "stand": "Halle 16, Stand A12, (30)",
        "product_link": "/aussteller/bundesamt-fur-sicherheit-bsi/N1567580",
        "search_snippet_type": "Aussteller 2025"
    },
    {
        "company_name": "Projektron",
        "location": "Berlin - DE",
        "description": "Die Projektron GmbH entwickelt und vertreibt seit 2001 mit derzeit mehr als 100 Mitarbeitern die webbasierte Projektmanagement-Software Projektron BCS. ...",
        "stand": "Halle 13, Stand C55",
        "product_link": "/aussteller/projektron/N1507610",
        "search_snippet_type": "Aussteller 2025"
    },
    {
        "company_name": "AVEVA",
        "location": "Frankfurt - DE",
        "description": "AVEVA ist ein weltweit führendes Unternehmen für Industriesoftware und entfacht den Einfallsreichtum, um den verantwortungsvollen Umgang mit den Ressourcen ...",
        "stand": "Halle 11, Stand C52",
        "product_link": "/aussteller/aveva/N1526345",
        "search_snippet_type": "Aussteller 2025"
    },
    {
        "company_name": "AVEVA",
        "location": "Cambridge CB3 0HB - GB",
        "description": "AVEVA ist ein weltweit führendes Unternehmen für Industriesoftware und entfacht den Einfallsreichtum, um den verantwortungsvollen Umgang mit den Ressourcen ...",
        "stand": "Halle 17, Stand G06",
        "product_link": "/aussteller/aveva/N1584610",
        "search_snippet_type": "Aussteller 2025"
    },
    {
        "company_name": "AVEVA",
        "location": "Cambridge CB3 0HB - GB",
        "description": "AVEVA ist ein weltweit führendes Unternehmen für Industriesoftware und entfacht den Einfallsreichtum, um den verantwortungsvollen Umgang mit den Ressourcen ...",
        "stand": "Halle 15, Stand D76",
        "product_link": "/aussteller/aveva/N1549574",
        "search_snippet_type": "Aussteller 2025"
    },
    {
        "company_name": "Box Deutschland",
        "location": "München - DE",
        "description": "Box ist die Intelligente Content Cloud: die Plattform für interne und externe Zusammenarbeit, integriert in andere Systeme (wie Salesforce oder MS Teams), ...",
        "stand": "Halle 15, Stand F28",
        "product_link": "/aussteller/box-deutschland/N1574180",
        "search_snippet_type": "Aussteller 2025"
    },
    {
        "company_name": "Cognite",
        "location": "Lysaker - NO",
        "description": "Cognite is a global industrial SaaS company that was established with one clear vision: to rapidly empower industrial companies with contextualized, ...",
        "stand": "Halle 17, Stand G06",
        "product_link": "/aussteller/cognite/N1483662",
        "search_snippet_type": "Aussteller 2025"
    },
    {
        "company_name": "Cognite",
        "location": "Lysaker - NO",
        "description": "Cognite is a global industrial SaaS company that was established with one clear vision: to rapidly empower industrial companies with contextualized, ...",
        "stand": "Halle 15, Stand D76",
        "product_link": "/aussteller/cognite/N1548298",
        "search_snippet_type": "Aussteller 2025"
    },
    {
        "company_name": "envyze",
        "location": "Hannover - DE",
        "description": "Wir navigieren Sie durch Ihre komplexen, nachhaltigen Energieprojekte! \n\nenvyze, eine Ausgründung des Teams „Nachhaltige Energielösungen“ der Cratos GmbH, ...",
        "stand": "Halle 13, Stand C61",
        "product_link": "/aussteller/envyze/N1571110",
        "search_snippet_type": "Aussteller 2025"
    }
]